print_python_hello/__init__.py
print_python_hello/hello.py
print_python_hello-0.1.0.dist-info/WHEEL
print_python_hello-0.1.0.dist-info/METADATA
print_python_hello-0.1.0.dist-info/RECORD
