Metadata-Version: 2.1
Name: print-python-hello
Version: 0.1.0
Summary: 
Author: YaroslavYaryk
Author-email: duhanov2003@gmail.com
Requires-Python: >=3.9,<4.0
Classifier: Programming Language :: Python :: 3
Classifier: Programming Language :: Python :: 3.10
Classifier: Programming Language :: Python :: 3.9
Requires-Dist: Django (>=4.0.3,<5.0.0)
Requires-Dist: requests (>=2.27.1,<3.0.0)
